webcubers/__init__.py
webcubers/core.py
webcubers/cubers.py
webcubers/webcubers.py
webcubers-1.8.1.dist-info/LICENSE
webcubers-1.8.1.dist-info/METADATA
webcubers-1.8.1.dist-info/WHEEL
webcubers-1.8.1.dist-info/entry_points.txt
webcubers-1.8.1.dist-info/top_level.txt
webcubers-1.8.1.dist-info/RECORD
