Metadata-Version: 2.1
Name: webcubers
Version: 1.8.1
Summary: webcubers python interface
Home-page: https://github.com/webcubers/webcubers-pypi
Author: WebCubers
Author-email: python@webcubers.com
License: UNKNOWN
Platform: UNKNOWN
Classifier: Programming Language :: Python :: 3
Classifier: License :: OSI Approved :: MIT License
Classifier: Operating System :: OS Independent
Requires-Dist: requests
Requires-Dist: appdirs
Requires-Dist: cutie
Requires-Dist: PTable
Requires-Dist: pyotp
